<annotation>
  <filename>1110</filename>
  <size>
    <width>2112</width>
    <height>1584</height>
    <depth>24</depth>
  </size>
  <segmented>2</segmented>
  <objects>
    <object>
      <id>77</id>
      <name>Achnanthidium biasolettianum</name>
      <bbox>
        <xmin>810</xmin>
        <xmax>1061</xmax>
        <ymin>1488</ymin>
        <ymax>1572</ymax>
      </bbox>
    </object>
    <object>
      <id>86</id>
      <name>Cymbella excisa</name>
      <bbox>
        <xmin>1113</xmin>
        <xmax>1480</xmax>
        <ymin>399</ymin>
        <ymax>763</ymax>
      </bbox>
    </object>
  </objects>
</annotation>