<annotation>
  <filename>1368</filename>
  <size>
    <width>2112</width>
    <height>1584</height>
    <depth>24</depth>
  </size>
  <segmented>2</segmented>
  <objects>
    <object>
      <id>35</id>
      <name>Navicula cryptotenella</name>
      <bbox>
        <xmin>1186</xmin>
        <xmax>1612</xmax>
        <ymin>531</ymin>
        <ymax>799</ymax>
      </bbox>
    </object>
    <object>
      <id>35</id>
      <name>Navicula cryptotenella</name>
      <bbox>
        <xmin>799</xmin>
        <xmax>1323</xmax>
        <ymin>558</ymin>
        <ymax>706</ymax>
      </bbox>
    </object>
  </objects>
</annotation>